iflow_sdk/__init__.py
iflow_sdk/_errors.py
iflow_sdk/client.py
iflow_sdk/query.py
iflow_sdk/raw_client.py
iflow_sdk/types.py
iflow_sdk/_internal/__init__.py
iflow_sdk/_internal/file_handler.py
iflow_sdk/_internal/process_manager.py
iflow_sdk/_internal/protocol.py
iflow_sdk/_internal/transport.py
iflow_cli_sdk-0.1.14.dist-info/licenses/LICENSE
iflow_cli_sdk-0.1.14.dist-info/WHEEL
iflow_cli_sdk-0.1.14.dist-info/METADATA
iflow_cli_sdk-0.1.14.dist-info/RECORD
