Metadata-Version: 2.4
Name: iflow-cli-sdk
Version: 0.1.14
Summary: Python SDK for iFlow CLI - AI Agent Integration
Keywords: iflow,ai,agent,llm,cli,acp,websocket,async,sdk,api,chatbot,automation
Author-email: iFlow Team <iflow@example.com>
Requires-Python: >=3.8
License-Expression: MIT
Classifier: Development Status :: 3 - Alpha
Classifier: Intended Audience :: Developers
Classifier: Programming Language :: Python :: 3
Classifier: Programming Language :: Python :: 3.8
Classifier: Programming Language :: Python :: 3.9
Classifier: Programming Language :: Python :: 3.10
Classifier: Programming Language :: Python :: 3.11
Classifier: Programming Language :: Python :: 3.12
Classifier: Topic :: Software Development :: Libraries
Classifier: Topic :: Software Development :: Libraries :: Python Modules
License-File: LICENSE
Requires-Dist: websockets>=11.0
Requires-Dist: aiohttp>=3.8.0
Requires-Dist: typing-extensions>=4.0.0; python_version<'3.11'
Requires-Dist: pydantic>=2.0.0
Requires-Dist: pytest>=7.0 ; extra == "dev"
Requires-Dist: pytest-asyncio>=0.21.0 ; extra == "dev"
Requires-Dist: pytest-cov>=4.0 ; extra == "dev"
Requires-Dist: black>=23.0 ; extra == "dev"
Requires-Dist: ruff>=0.1.0 ; extra == "dev"
Requires-Dist: mypy>=1.0 ; extra == "dev"
Requires-Dist: types-aiofiles ; extra == "dev"
Project-URL: Documentation, https://docs.iflow.ai/sdk/python
Project-URL: Homepage, https://github.com/iflow/iflow-sdk-python
Project-URL: Issues, https://github.com/iflow/iflow-sdk-python/issues
Project-URL: Repository, https://github.com/iflow/iflow-sdk-python
Provides-Extra: dev
